pytest_api_soup/.gitkeep
pytest_api_soup/__init__.py
pytest_api_soup-0.0.2.dist-info/LICENSE
pytest_api_soup-0.0.2.dist-info/WHEEL
pytest_api_soup-0.0.2.dist-info/METADATA
pytest_api_soup-0.0.2.dist-info/RECORD
