Metadata-Version: 2.1
Name: pytest-api-soup
Version: 0.0.2
Summary: Validate multiple endpoints with unit testing using a single source of truth.
Author: Indi Harrington
Author-email: indigoharrington@gmail.com
Requires-Python: >=3.10,<4.0
Classifier: Programming Language :: Python :: 3
Classifier: Programming Language :: Python :: 3.10
